CREDITS.md
LICENSE.txt
MANIFEST.in
README.md
setup.py
PyTraffic/LicensePlate.py
PyTraffic/PeopleDetection.py
PyTraffic/VehicleDetection.py
PyTraffic/__init__.py
PyTraffic.egg-info/PKG-INFO
PyTraffic.egg-info/SOURCES.txt
PyTraffic.egg-info/dependency_links.txt
PyTraffic.egg-info/requires.txt
PyTraffic.egg-info/top_level.txt
PyTraffic/models/haarcascade_car.xml
PyTraffic/models/haarcascade_russian_plate_number.xml
PyTraffic/sample_media/LicensePlate/images/1.jpg
PyTraffic/sample_media/LicensePlate/images/2.jpg
PyTraffic/sample_media/LicensePlate/images/3.jpg
PyTraffic/sample_media/LicensePlate/images/4.jpg
PyTraffic/sample_media/LicensePlate/images/5.jpg
PyTraffic/sample_media/LicensePlate/images/6.jpg
PyTraffic/sample_media/LicensePlate/images/7.jpg
PyTraffic/sample_media/LicensePlate/images/8.jpg
PyTraffic/sample_media/PeopleDetection/videos/1.mp4
PyTraffic/sample_media/PeopleDetection/videos/2.mp4
PyTraffic/sample_media/PeopleDetection/videos/3.mp4
PyTraffic/sample_media/PeopleDetection/videos/4.mp4
PyTraffic/sample_media/PeopleDetection/videos/5.mp4
PyTraffic/sample_media/VehicleDetection/images/1.jpg
PyTraffic/sample_media/VehicleDetection/images/10.jpg
PyTraffic/sample_media/VehicleDetection/images/2.jpg
PyTraffic/sample_media/VehicleDetection/images/3.jpg
PyTraffic/sample_media/VehicleDetection/images/4.jpg
PyTraffic/sample_media/VehicleDetection/images/5.jpg
PyTraffic/sample_media/VehicleDetection/images/6.jpg
PyTraffic/sample_media/VehicleDetection/images/7.jpg
PyTraffic/sample_media/VehicleDetection/images/8.jpg
PyTraffic/sample_media/VehicleDetection/images/9.jpg
PyTraffic/sample_media/VehicleDetection/videos/1.mp4