Metadata-Version: 2.1
Name: PyTraffic
Version: 1.1.8
Summary: PyTraffic is an advanced Python package to work on traffic-related functions and use cases.
Home-page: https://github.com/Anikethc/PyTraffic
Download-URL: https://pypi.org/project/PyTraffic
Author: Aniketh Chavare
Author-email: anikethchavare@outlook.com
License: MIT
Keywords: Traffic,Traffic Density,Traffic Density Estimation,License Plates,License Plate Detection,License Plate Recognition,Vehicles,Vehicle Detection
License-File: LICENSE.txt
